antlr4/BufferedTokenStream.py
antlr4/CommonTokenFactory.py
antlr4/CommonTokenStream.py
antlr4/FileStream.py
antlr4/InputStream.py
antlr4/IntervalSet.py
antlr4/LL1Analyzer.py
antlr4/Lexer.py
antlr4/ListTokenSource.py
antlr4/Parser.py
antlr4/ParserInterpreter.py
antlr4/ParserRuleContext.py
antlr4/PredictionContext.py
antlr4/Recognizer.py
antlr4/RuleContext.py
antlr4/StdinStream.py
antlr4/Token.py
antlr4/TokenStreamRewriter.py
antlr4/Utils.py
antlr4/__init__.py
antlr4/_pygrun.py
antlr4/atn/ATN.py
antlr4/atn/ATNConfig.py
antlr4/atn/ATNConfigSet.py
antlr4/atn/ATNDeserializationOptions.py
antlr4/atn/ATNDeserializer.py
antlr4/atn/ATNSimulator.py
antlr4/atn/ATNState.py
antlr4/atn/ATNType.py
antlr4/atn/LexerATNSimulator.py
antlr4/atn/LexerAction.py
antlr4/atn/LexerActionExecutor.py
antlr4/atn/ParserATNSimulator.py
antlr4/atn/PredictionMode.py
antlr4/atn/SemanticContext.py
antlr4/atn/Transition.py
antlr4/atn/__init__.py
antlr4/dfa/DFA.py
antlr4/dfa/DFASerializer.py
antlr4/dfa/DFAState.py
antlr4/dfa/__init__.py
antlr4/error/DiagnosticErrorListener.py
antlr4/error/ErrorListener.py
antlr4/error/ErrorStrategy.py
antlr4/error/Errors.py
antlr4/error/__init__.py
antlr4/tree/Chunk.py
antlr4/tree/ParseTreeMatch.py
antlr4/tree/ParseTreePattern.py
antlr4/tree/ParseTreePatternMatcher.py
antlr4/tree/RuleTagToken.py
antlr4/tree/TokenTagToken.py
antlr4/tree/Tree.py
antlr4/tree/Trees.py
antlr4/tree/__init__.py
antlr4/xpath/XPath.py
antlr4/xpath/XPathLexer.py
antlr4/xpath/__init__.py
antlr4_python3_runtime-4.13.1.dist-info/METADATA
antlr4_python3_runtime-4.13.1.dist-info/WHEEL
antlr4_python3_runtime-4.13.1.dist-info/entry_points.txt
antlr4_python3_runtime-4.13.1.dist-info/top_level.txt
antlr4_python3_runtime-4.13.1.dist-info/RECORD
